{"data":{"questions":[{"id":1558,"content":"Welche Auffassungen werden zur Frage des Zugangs bei mündlichen Willenserklärungen vertreten?","answer":"- aA: strenge Vernehmungstheorie - Zugang liegt erst dann vor, wenn der Erklärungsempfänger die Erklärung richtig verstanden hat.\n- hM: eingeschränkte Vernehmungstheorie - Zugang liegt vor, wenn der Erklärende davon ausgehen durfte, dass der Erklärungsempfänger die Erklärung richtig verstanden hat.","learn_unit_id":9,"created":"2012-11-15 23:24:47 +0100","position":1,"annotation":{"id":1558,"creator_id":null,"created":"2012-11-15 23:24:47 +0100","video_id":13,"start_sec":24,"end_sec":136,"law_text_id":null,"question_id":1558,"video_note_id":null}},{"id":1559,"content":"Was spricht für die strenge Vernehmungstheorie?","answer":"Schutz des Erklärungsempfängers.","learn_unit_id":9,"created":"2012-11-15 23:24:47 +0100","position":2,"annotation":{"id":1559,"creator_id":null,"created":"2012-11-15 23:24:47 +0100","video_id":13,"start_sec":136,"end_sec":166,"law_text_id":null,"question_id":1559,"video_note_id":null}},{"id":1560,"content":"Was spricht für die eingeschränkte Vernehmungstheorie?","answer":"Die konsequente Anwendung der allgemeinen Zugangsdefinition auf die Situation der mündlichen Willenserklärung - auch sonst kommt es nicht darauf an, ob der Empfänger Kenntnis von der Erklärung erlangt hat.","learn_unit_id":9,"created":"2012-11-15 23:24:47 +0100","position":3,"annotation":{"id":1560,"creator_id":null,"created":"2012-11-15 23:24:47 +0100","video_id":13,"start_sec":166,"end_sec":210,"law_text_id":null,"question_id":1560,"video_note_id":null}}]}}